README.rst
setup.py
InternetArgumentCorpus.egg-info/PKG-INFO
InternetArgumentCorpus.egg-info/SOURCES.txt
InternetArgumentCorpus.egg-info/dependency_links.txt
InternetArgumentCorpus.egg-info/requires.txt
InternetArgumentCorpus.egg-info/top_level.txt
iacorpus/__init__.py
iacorpus/example.py
iacorpus/iac_objects.py
iacorpus/datasets/__init__.py
iacorpus/datasets/convote.py
iacorpus/datasets/createdebate.py
iacorpus/datasets/fourforums.py
iacorpus/datasets/convinceme/__init__.py
iacorpus/datasets/convinceme/convinceme.py
iacorpus/datasets/generic/__init__.py
iacorpus/datasets/generic/dataset.py
iacorpus/datasets/generic/orm/__init__.py
iacorpus/datasets/generic/orm/dependency.py
iacorpus/datasets/generic/orm/discussion.py
iacorpus/datasets/generic/orm/post.py
iacorpus/datasets/generic/orm/quote.py
iacorpus/datasets/generic/orm/text.py
iacorpus/datasets/generic/orm/token.py
iacorpus/initialization/__init__.py
iacorpus/initialization/dataset_importer.py
iacorpus/initialization/iac_html_parser.py
iacorpus/initialization/quote_finder.py
iacorpus/initialization/raw_data_loader.py
iacorpus/initialization/convinceme/__init__.py
iacorpus/initialization/convote/__init__.py
iacorpus/initialization/convote/convote_importer.py
iacorpus/initialization/createdebate/__init__.py
iacorpus/initialization/createdebate/createdebate_html_parser.py
iacorpus/initialization/fourforums/__init__.py
iacorpus/initialization/parsing/__init__.py
iacorpus/initialization/parsing/step1_db_to_disk.py
iacorpus/initialization/parsing/step2_do_parsing.py
iacorpus/initialization/parsing/step4_store_parse.py
iacorpus/utilities/__init__.py
iacorpus/utilities/misc/__init__.py
iacorpus/utilities/misc/_lazy_property.py
iacorpus/utilities/misc/_progress_reporter.py
iacorpus/utilities/misc/_random_guard.py
iacorpus/utilities/misc/_tablerepr.py
iacorpus/utilities/misc/itertools_recipes.py
iacorpus/utilities/nlp/__init__.py
iacorpus/utilities/nlp/corenlp_mine.py