Metadata-Version: 1.1
Name: InternetArgumentCorpus
Version: 1.0.1
Summary: The Internet Argument Corpus (IAC) version 2 is a collection of corpora for research in political debate on internet forums.
Home-page: https://bitbucket.org/nlds_iac/internet-argument-corpus-2
Author: Rob Abbott
Author-email: abbott@soe.ucsc.edu
License: MIT
Download-URL: https://bitbucket.org/nlds_iac/internet-argument-corpus-2/get/1.0.1.tar.gz
Keywords: corpus
Platform: UNKNOWN
